{"total":59939471,"insurance":42013254,"self_pay":17426807,"customers":788,"facilities":26,"new_customers":22,"lost_customers":11,"net_customers":11,"prev_total":57208861,"prev_insurance":40066505,"prev_self_pay":16745245,"prev_customers":773,"prev_month":"2026-01","change_total_pct":4.8,"change_insurance_pct":4.9,"change_self_pay_pct":4.1,"change_customers_pct":1.9,"change_non_sale_pct":0,"non_sale":0,"prev_non_sale":0,"avg_per_customer":76065,"avg_per_facility":2305364,"avg_ins_per_customer":53316,"avg_pay_per_customer":22115,"status_sentence":"売上 ¥59.9M（前月比 +4.8%） ｜ 利用者 788名 ｜ 新規22名・終了11名 ｜ 26拠点"}